persistqueue/__init__.py
persistqueue/exceptions.py
persistqueue/mysqlqueue.py
persistqueue/pdict.py
persistqueue/queue.py
persistqueue/sqlackqueue.py
persistqueue/sqlbase.py
persistqueue/sqlqueue.py
persistqueue/serializers/__init__.py
persistqueue/serializers/cbor2.py
persistqueue/serializers/json.py
persistqueue/serializers/msgpack.py
persistqueue/serializers/pickle.py
persistqueue/tests/__init__.py
persistqueue/tests/test_mysqlqueue.py
persistqueue/tests/test_pdict.py
persistqueue/tests/test_queue.py
persistqueue/tests/test_sqlackqueue.py
persistqueue/tests/test_sqlqueue.py
persist_queue-1.0.0.dist-info/LICENSE
persist_queue-1.0.0.dist-info/METADATA
persist_queue-1.0.0.dist-info/WHEEL
persist_queue-1.0.0.dist-info/top_level.txt
persist_queue-1.0.0.dist-info/RECORD
