Metadata-Version: 2.1
Name: persist-queue
Version: 1.0.0
Summary: A thread-safe disk based persistent queue in Python.
Home-page: http://github.com/peter-wangxu/persist-queue
Author: Peter Wang
Author-email: wangxu198709@gmail.com
Maintainer: Peter Wang
Maintainer-email: wangxu198709@gmail.com
License: BSD
Platform: all
Classifier: Development Status :: 4 - Beta
Classifier: Operating System :: OS Independent
Classifier: Intended Audience :: Developers
Classifier: License :: OSI Approved :: BSD License
Classifier: Programming Language :: Python
Classifier: Programming Language :: Python :: Implementation
Classifier: Programming Language :: Python :: 3
Classifier: Programming Language :: Python :: 3.8
Classifier: Programming Language :: Python :: 3.9
Classifier: Programming Language :: Python :: 3.10
Classifier: Programming Language :: Python :: 3.11
Classifier: Programming Language :: Python :: 3.12
Classifier: Topic :: Software Development :: Libraries
License-File: LICENSE
Provides-Extra: extra
Requires-Dist: msgpack >=0.5.6 ; extra == 'extra'
Requires-Dist: cbor2 >=5.2.0 ; extra == 'extra'
Requires-Dist: PyMySQL ; extra == 'extra'
Requires-Dist: DBUtils <3.0.0 ; extra == 'extra'
